idflow/__init__.py
idflow/docker.py
idflow/flow.py
idflow/utils.py
invoke_docker_flow-0.0.13.dist-info/DESCRIPTION.rst
invoke_docker_flow-0.0.13.dist-info/METADATA
invoke_docker_flow-0.0.13.dist-info/RECORD
invoke_docker_flow-0.0.13.dist-info/WHEEL
invoke_docker_flow-0.0.13.dist-info/metadata.json
invoke_docker_flow-0.0.13.dist-info/top_level.txt
